Changes.rst
LICENSE
README.rst
setup.cfg
setup.py
./dugong/__init__.py
doc/html/.buildinfo
doc/html/api.html
doc/html/coroutines.html
doc/html/genindex.html
doc/html/index.html
doc/html/intro.html
doc/html/issues.html
doc/html/objects.inv
doc/html/search.html
doc/html/searchindex.js
doc/html/tutorial.html
doc/html/whatsnew.html
doc/html/_sources/api.rst.txt
doc/html/_sources/coroutines.rst.txt
doc/html/_sources/index.rst.txt
doc/html/_sources/intro.rst.txt
doc/html/_sources/issues.rst.txt
doc/html/_sources/tutorial.rst.txt
doc/html/_sources/whatsnew.rst.txt
doc/html/_static/ajax-loader.gif
doc/html/_static/basic.css
doc/html/_static/classic.css
doc/html/_static/comment-bright.png
doc/html/_static/comment-close.png
doc/html/_static/comment.png
doc/html/_static/default.css
doc/html/_static/doctools.js
doc/html/_static/documentation_options.js
doc/html/_static/down-pressed.png
doc/html/_static/down.png
doc/html/_static/file.png
doc/html/_static/jquery-3.2.1.js
doc/html/_static/jquery.js
doc/html/_static/language_data.js
doc/html/_static/minus.png
doc/html/_static/plus.png
doc/html/_static/pygments.css
doc/html/_static/searchtools.js
doc/html/_static/sidebar.js
doc/html/_static/underscore-1.3.1.js
doc/html/_static/underscore.js
doc/html/_static/up-pressed.png
doc/html/_static/up.png
doc/html/_static/websupport.js
dugong.egg-info/PKG-INFO
dugong.egg-info/SOURCES.txt
dugong.egg-info/dependency_links.txt
dugong.egg-info/top_level.txt
dugong.egg-info/zip-safe
examples/extract_links.py
examples/httpcat.py
examples/pipeline1.py
rst/api.rst
rst/conf.py
rst/coroutines.rst
rst/index.rst
rst/intro.rst
rst/issues.rst
rst/tutorial.rst
rst/whatsnew.rst
rst/_templates/localtoc.html
test/ca.crt
test/ca.key
test/conftest.py
test/pytest.ini
test/pytest_checklogs.py
test/server.crt
test/server.key
test/test_aio.py
test/test_dugong.py
test/test_examples.py
test/travis-install.sh
test/travis-test.sh
test/.pytest_cache/.gitignore
test/.pytest_cache/CACHEDIR.TAG
test/.pytest_cache/README.md
test/.pytest_cache/v/cache/lastfailed
test/.pytest_cache/v/cache/nodeids
test/.pytest_cache/v/cache/stepwise