Metadata-Version: 1.1
Name: dugong
Version: 3.8.2
Summary: A HTTP 1.1 client module supporting asynchronous IO, pipelining and `Expect: 100-continue`. Designed for RESTful protocols.
Home-page: https://github.com/python-dugong/python-dugong/
Author: Nikolaus Rath
Author-email: Nikolaus@rath.org
License: PSF
Keywords: http
Platform: UNKNOWN
Classifier: Programming Language :: Python :: 3
Classifier: Development Status :: 5 - Production/Stable
Classifier: Intended Audience :: Developers
Classifier: License :: OSI Approved :: Python Software Foundation License
Classifier: Topic :: Internet :: WWW/HTTP
Classifier: Topic :: Software Development :: Libraries :: Python Modules
Provides: dugong
